{
  "metadata": {
    "timestamp": "2026-03-06T08:39:58.336",
    "date": "2026-03-06",
    "facility": "Main Plant"
  },
  "shifts": [
    {
      "id": "normal-time",
      "name": "Fri 7h NT A",
      "startTime": "07:30",
      "endTime": "15:15",
      "breaks": [
        {
          "type": "tea",
          "startTime": "10:25",
          "endTime": "10:45"
        },
        {
          "type": "lunch",
          "startTime": "13:40",
          "endTime": "14:15"
        }
      ],
      "availableWorkHours": 6.833333333
    }
  ],
  "production": [
    {
      "id": "3rd_Line-UBT-UBT",
      "productionLine": "3rd_Line",
      "product": {
        "id": "UBT",
        "name": "UBT"
      },
      "variant": {
        "id": "UBT",
        "name": "UBT",
        "fullName": "UBT UBT",
        "cycleTime": 58.24,
        "devicesPerBox": 25,
        "actualCycleTime": 165.6
      },
      "shiftId": "normal-time",
      "targets": {
        "hourly": 61,
        "daily": 509,
        "boxes": 20
      },
      "actual": {
        "total": 25,
        "boxes": 1,
        "progress": 5
      },
      "batches": [
        {
          "id": 26030205,
          "quantity": 25,
          "boxes": 1
        }
      ],
      "lineWindow": {
        "startTime": "07:30",
        "endTime": "15:15",
        "target": 422,
        "production": 25,
        "progress": 6
      },
      "timeline": [
        {
          "hour": "08:30",
          "target": 61,
          "actual": 25,
          "cumTarget": 61,
          "cumActual": 25,
          "transitionTarget": 0,
          "previousVariant": null,
          "previousVariantMinutes": 0,
          "currentVariantMinutes": 60
        },
        {
          "hour": "09:30",
          "target": 61,
          "actual": 0,
          "cumTarget": 122,
          "cumActual": 25,
          "transitionTarget": 0,
          "previousVariant": null,
          "previousVariantMinutes": 0,
          "currentVariantMinutes": 60
        }
      ]
    },
    {
      "id": "LEVO-LEVO-XL2200SD",
      "productionLine": "LEVO",
      "product": {
        "id": "LEVO",
        "name": "LEVO"
      },
      "variant": {
        "id": "XL2200SD",
        "name": "XL2200SD",
        "fullName": "LEVO XL2200SD",
        "cycleTime": 97.06,
        "devicesPerBox": 8,
        "actualCycleTime": 258.75
      },
      "shiftId": "normal-time",
      "targets": {
        "hourly": 37,
        "daily": 305,
        "boxes": 38
      },
      "actual": {
        "total": 16,
        "boxes": 2,
        "progress": 5
      },
      "batches": [
        {
          "id": 26030517,
          "quantity": 16,
          "boxes": 2
        }
      ],
      "lineWindow": {
        "startTime": "07:30",
        "endTime": "15:15",
        "target": 253,
        "production": 16,
        "progress": 6
      },
      "timeline": [
        {
          "hour": "08:30",
          "target": 37,
          "actual": 0,
          "cumTarget": 37,
          "cumActual": 0,
          "transitionTarget": 0,
          "previousVariant": null,
          "previousVariantMinutes": 0,
          "currentVariantMinutes": 60
        },
        {
          "hour": "09:30",
          "target": 37,
          "actual": 16,
          "cumTarget": 74,
          "cumActual": 16,
          "transitionTarget": 0,
          "previousVariant": null,
          "previousVariantMinutes": 0,
          "currentVariantMinutes": 60
        }
      ]
    },
    {
      "id": "Scalpel_Assembly-Scalpel-PAHS15S",
      "productionLine": "Scalpel_Assembly",
      "product": {
        "id": "Scalpel",
        "name": "Scalpel"
      },
      "variant": {
        "id": "PAHS15S",
        "name": "PAHS15S",
        "fullName": "Scalpel PAHS15S",
        "cycleTime": 2.28,
        "devicesPerBox": 500,
        "actualCycleTime": 2.07
      },
      "shiftId": "normal-time",
      "targets": {
        "hourly": 1578,
        "daily": 13026,
        "boxes": 26
      },
      "actual": {
        "total": 2000,
        "boxes": 0,
        "progress": 15
      },
      "batches": [
        {
          "id": 26030521,
          "quantity": 2000,
          "boxes": 0
        }
      ],
      "lineWindow": {
        "startTime": "07:30",
        "endTime": "15:15",
        "target": 10789,
        "production": 2000,
        "progress": 19
      },
      "timeline": [
        {
          "hour": "08:30",
          "target": 1578,
          "actual": 0,
          "cumTarget": 1578,
          "cumActual": 0,
          "transitionTarget": 0,
          "previousVariant": null,
          "previousVariantMinutes": 0,
          "currentVariantMinutes": 60
        },
        {
          "hour": "09:30",
          "target": 1578,
          "actual": 2000,
          "cumTarget": 3156,
          "cumActual": 2000,
          "transitionTarget": 0,
          "previousVariant": null,
          "previousVariantMinutes": 0,
          "currentVariantMinutes": 60
        }
      ]
    },
    {
      "id": "SCD-SCD-XL1000+",
      "productionLine": "SCD",
      "product": {
        "id": "SCD",
        "name": "SCD"
      },
      "variant": {
        "id": "XL1000+",
        "name": "XL1000+",
        "fullName": "SCD XL1000+",
        "cycleTime": 29.41,
        "devicesPerBox": 12,
        "actualCycleTime": 34.5
      },
      "shiftId": "normal-time",
      "targets": {
        "hourly": 122,
        "daily": 1224,
        "boxes": 102
      },
      "actual": {
        "total": 120,
        "boxes": 10,
        "progress": 10
      },
      "batches": [
        {
          "id": 26030519,
          "quantity": 120,
          "boxes": 10
        }
      ],
      "lineWindow": {
        "startTime": "07:30",
        "endTime": "15:15",
        "target": 836,
        "production": 120,
        "progress": 14
      },
      "timeline": [
        {
          "hour": "08:30",
          "target": 122,
          "actual": 120,
          "cumTarget": 122,
          "cumActual": 120,
          "transitionTarget": 0,
          "previousVariant": null,
          "previousVariantMinutes": 0,
          "currentVariantMinutes": 60
        },
        {
          "hour": "09:30",
          "target": 122,
          "actual": 0,
          "cumTarget": 244,
          "cumActual": 120,
          "transitionTarget": 0,
          "previousVariant": null,
          "previousVariantMinutes": 0,
          "currentVariantMinutes": 60
        }
      ]
    },
    {
      "id": "SUM-SUM-500V2",
      "productionLine": "SUM",
      "product": {
        "id": "SUM",
        "name": "SUM"
      },
      "variant": {
        "id": "500V2",
        "name": "500V2",
        "fullName": "SUM SUM500V2",
        "cycleTime": 26.47,
        "devicesPerBox": 20,
        "actualCycleTime": 51.75
      },
      "shiftId": "normal-time",
      "targets": {
        "hourly": 136,
        "daily": 1360,
        "boxes": 68
      },
      "actual": {
        "total": 80,
        "boxes": 4,
        "progress": 6
      },
      "batches": [
        {
          "id": 26030412,
          "quantity": 80,
          "boxes": 4
        }
      ],
      "lineWindow": {
        "startTime": "07:30",
        "endTime": "15:15",
        "target": 929,
        "production": 80,
        "progress": 9
      },
      "timeline": [
        {
          "hour": "08:30",
          "target": 136,
          "actual": 80,
          "cumTarget": 136,
          "cumActual": 80,
          "transitionTarget": 0,
          "previousVariant": null,
          "previousVariantMinutes": 0,
          "currentVariantMinutes": 60
        },
        {
          "hour": "09:30",
          "target": 136,
          "actual": 0,
          "cumTarget": 272,
          "cumActual": 80,
          "transitionTarget": 0,
          "previousVariant": null,
          "previousVariantMinutes": 0,
          "currentVariantMinutes": 60
        }
      ]
    }
  ],
  "lineCards": [
    {
      "id": "3rd_Line",
      "productionLine": "3rd_Line",
      "shiftId": "normal-time",
      "shiftName": "Fri 7h NT A",
      "startTime": "07:30",
      "endTime": "15:15",
      "totalProduction": 25,
      "totalTarget": 422,
      "progress": 6,
      "variants": [
        {
          "combinedId": "3rd_Line-UBT-UBT",
          "productName": "UBT",
          "variantName": "UBT",
          "variantFull": "UBT UBT",
          "cycleTime": 58.24,
          "actualCT": 165.6,
          "devicesPerBox": 25,
          "target": 422,
          "production": 25,
          "boxes": 1,
          "progress": 6,
          "startTime": "07:30",
          "endTime": "15:15",
          "timeline": [
            {
              "hour": "08:30",
              "target": 61,
              "actual": 25,
              "cumTarget": 61,
              "cumActual": 25,
              "transitionTarget": 0,
              "previousVariant": null,
              "previousVariantMinutes": 0,
              "currentVariantMinutes": 60
            },
            {
              "hour": "09:30",
              "target": 61,
              "actual": 0,
              "cumTarget": 122,
              "cumActual": 25,
              "transitionTarget": 0,
              "previousVariant": null,
              "previousVariantMinutes": 0,
              "currentVariantMinutes": 60
            }
          ]
        }
      ]
    },
    {
      "id": "LEVO",
      "productionLine": "LEVO",
      "shiftId": "normal-time",
      "shiftName": "Fri 7h NT A",
      "startTime": "07:30",
      "endTime": "15:15",
      "totalProduction": 16,
      "totalTarget": 253,
      "progress": 6,
      "variants": [
        {
          "combinedId": "LEVO-LEVO-XL2200SD",
          "productName": "LEVO",
          "variantName": "XL2200SD",
          "variantFull": "LEVO XL2200SD",
          "cycleTime": 97.06,
          "actualCT": 258.75,
          "devicesPerBox": 8,
          "target": 253,
          "production": 16,
          "boxes": 2,
          "progress": 6,
          "startTime": "07:30",
          "endTime": "15:15",
          "timeline": [
            {
              "hour": "08:30",
              "target": 37,
              "actual": 0,
              "cumTarget": 37,
              "cumActual": 0,
              "transitionTarget": 0,
              "previousVariant": null,
              "previousVariantMinutes": 0,
              "currentVariantMinutes": 60
            },
            {
              "hour": "09:30",
              "target": 37,
              "actual": 16,
              "cumTarget": 74,
              "cumActual": 16,
              "transitionTarget": 0,
              "previousVariant": null,
              "previousVariantMinutes": 0,
              "currentVariantMinutes": 60
            }
          ]
        }
      ]
    },
    {
      "id": "Scalpel_Assembly",
      "productionLine": "Scalpel_Assembly",
      "shiftId": "normal-time",
      "shiftName": "Fri 7h NT A",
      "startTime": "07:30",
      "endTime": "15:15",
      "totalProduction": 2000,
      "totalTarget": 10789,
      "progress": 19,
      "variants": [
        {
          "combinedId": "Scalpel_Assembly-Scalpel-PAHS15S",
          "productName": "Scalpel",
          "variantName": "PAHS15S",
          "variantFull": "Scalpel PAHS15S",
          "cycleTime": 2.28,
          "actualCT": 2.07,
          "devicesPerBox": 500,
          "target": 10789,
          "production": 2000,
          "boxes": 0,
          "progress": 19,
          "startTime": "07:30",
          "endTime": "15:15",
          "timeline": [
            {
              "hour": "08:30",
              "target": 1578,
              "actual": 0,
              "cumTarget": 1578,
              "cumActual": 0,
              "transitionTarget": 0,
              "previousVariant": null,
              "previousVariantMinutes": 0,
              "currentVariantMinutes": 60
            },
            {
              "hour": "09:30",
              "target": 1578,
              "actual": 2000,
              "cumTarget": 3156,
              "cumActual": 2000,
              "transitionTarget": 0,
              "previousVariant": null,
              "previousVariantMinutes": 0,
              "currentVariantMinutes": 60
            }
          ]
        }
      ]
    },
    {
      "id": "SCD",
      "productionLine": "SCD",
      "shiftId": "normal-time",
      "shiftName": "Fri 7h NT A",
      "startTime": "07:30",
      "endTime": "15:15",
      "totalProduction": 120,
      "totalTarget": 836,
      "progress": 14,
      "variants": [
        {
          "combinedId": "SCD-SCD-XL1000+",
          "productName": "SCD",
          "variantName": "XL1000+",
          "variantFull": "SCD XL1000+",
          "cycleTime": 29.41,
          "actualCT": 34.5,
          "devicesPerBox": 12,
          "target": 836,
          "production": 120,
          "boxes": 10,
          "progress": 14,
          "startTime": "07:30",
          "endTime": "15:15",
          "timeline": [
            {
              "hour": "08:30",
              "target": 122,
              "actual": 120,
              "cumTarget": 122,
              "cumActual": 120,
              "transitionTarget": 0,
              "previousVariant": null,
              "previousVariantMinutes": 0,
              "currentVariantMinutes": 60
            },
            {
              "hour": "09:30",
              "target": 122,
              "actual": 0,
              "cumTarget": 244,
              "cumActual": 120,
              "transitionTarget": 0,
              "previousVariant": null,
              "previousVariantMinutes": 0,
              "currentVariantMinutes": 60
            }
          ]
        }
      ]
    },
    {
      "id": "SUM",
      "productionLine": "SUM",
      "shiftId": "normal-time",
      "shiftName": "Fri 7h NT A",
      "startTime": "07:30",
      "endTime": "15:15",
      "totalProduction": 80,
      "totalTarget": 929,
      "progress": 9,
      "variants": [
        {
          "combinedId": "SUM-SUM-500V2",
          "productName": "SUM",
          "variantName": "500V2",
          "variantFull": "SUM SUM500V2",
          "cycleTime": 26.47,
          "actualCT": 51.75,
          "devicesPerBox": 20,
          "target": 929,
          "production": 80,
          "boxes": 4,
          "progress": 9,
          "startTime": "07:30",
          "endTime": "15:15",
          "timeline": [
            {
              "hour": "08:30",
              "target": 136,
              "actual": 80,
              "cumTarget": 136,
              "cumActual": 80,
              "transitionTarget": 0,
              "previousVariant": null,
              "previousVariantMinutes": 0,
              "currentVariantMinutes": 60
            },
            {
              "hour": "09:30",
              "target": 136,
              "actual": 0,
              "cumTarget": 272,
              "cumActual": 80,
              "transitionTarget": 0,
              "previousVariant": null,
              "previousVariantMinutes": 0,
              "currentVariantMinutes": 60
            }
          ]
        }
      ]
    }
  ],
  "lineGroups": [],
  "summary": {
    "products": [
      {
        "id": "UBT",
        "name": "UBT",
        "totalProduction": 25,
        "totalTarget": 509,
        "progress": 5
      },
      {
        "id": "LEVO",
        "name": "LEVO",
        "totalProduction": 16,
        "totalTarget": 305,
        "progress": 5
      },
      {
        "id": "Scalpel",
        "name": "Scalpel",
        "totalProduction": 2000,
        "totalTarget": 13026,
        "progress": 15
      },
      {
        "id": "SCD",
        "name": "SCD",
        "totalProduction": 120,
        "totalTarget": 1224,
        "progress": 10
      },
      {
        "id": "SUM",
        "name": "SUM",
        "totalProduction": 80,
        "totalTarget": 1360,
        "progress": 6
      }
    ],
    "productionLines": [
      {
        "id": "SCD",
        "name": "SCD",
        "totalProduction": 120,
        "totalTarget": 836,
        "progress": 14,
        "variants": [
          "SCD-SCD-XL1000+"
        ],
        "shiftId": "normal-time",
        "startTime": "07:30",
        "endTime": "15:15"
      },
      {
        "id": "SUM",
        "name": "SUM",
        "totalProduction": 80,
        "totalTarget": 929,
        "progress": 9,
        "variants": [
          "SUM-SUM-500V2"
        ],
        "shiftId": "normal-time",
        "startTime": "07:30",
        "endTime": "15:15"
      },
      {
        "id": "3rd_Line",
        "name": "3rd_Line",
        "totalProduction": 25,
        "totalTarget": 422,
        "progress": 6,
        "variants": [
          "3rd_Line-UBT-UBT"
        ],
        "shiftId": "normal-time",
        "startTime": "07:30",
        "endTime": "15:15"
      },
      {
        "id": "Scalpel_Assembly",
        "name": "Scalpel_Assembly",
        "totalProduction": 2000,
        "totalTarget": 10789,
        "progress": 19,
        "variants": [
          "Scalpel_Assembly-Scalpel-PAHS15S"
        ],
        "shiftId": "normal-time",
        "startTime": "07:30",
        "endTime": "15:15"
      },
      {
        "id": "LEVO",
        "name": "LEVO",
        "totalProduction": 16,
        "totalTarget": 253,
        "progress": 6,
        "variants": [
          "LEVO-LEVO-XL2200SD"
        ],
        "shiftId": "normal-time",
        "startTime": "07:30",
        "endTime": "15:15"
      }
    ]
  }
}