{
  "metadata": {
    "timestamp": "2026-02-23T09:23:15.596Z",
    "date": "2026-02-23",
    "facility": "Main Plant"
  },
  "shifts": [
    {
      "id": "normal-time",
      "name": "8.25h NT A",
      "startTime": "07:30",
      "endTime": "16:30",
      "breaks": [
        {
          "type": "tea",
          "startTime": "10:25",
          "endTime": "10:45"
        },
        {
          "type": "lunch",
          "startTime": "13:40",
          "endTime": "14:15"
        }
      ],
      "availableWorkHours": 8.083333333333334
    }
  ],
  "production": [
    {
      "id": "SCD-XL1000SC",
      "product": {
        "id": "SCD",
        "name": "SCD"
      },
      "variant": {
        "id": "XL1000SC",
        "name": "XL1000SC",
        "fullName": "SCD XL1000SC",
        "cycleTime": 29.41,
        "devicesPerBox": 12,
        "actualCycleTime": 690
      },
      "shiftId": "normal-time",
      "targets": {
        "hourly": 122,
        "daily": 989,
        "boxes": 82
      },
      "actual": {
        "total": 36,
        "boxes": 3,
        "progress": 4
      },
      "batches": [
        {
          "id": 26021957,
          "quantity": 36,
          "boxes": 3
        }
      ],
      "supervisors": [
        {
          "id": "Michaela",
          "name": "Michaela",
          "production": 36,
          "startTime": "08:41",
          "endTime": "16:30",
          "target": 844,
          "progress": 4
        }
      ],
      "timeline": [
        {
          "hour": "08:30",
          "target": 122,
          "actual": 0,
          "cumTarget": 122,
          "cumActual": 0,
          "transitionTarget": 0,
          "previousVariant": null,
          "previousVariantMinutes": 0,
          "currentVariantMinutes": 60
        },
        {
          "hour": "09:30",
          "target": 99,
          "actual": 36,
          "cumTarget": 221,
          "cumActual": 36,
          "transitionTarget": 99,
          "previousVariant": "SCD-XL1000+",
          "previousVariantMinutes": 11,
          "currentVariantMinutes": 49
        }
      ]
    },
    {
      "id": "SCD-XL1000+",
      "product": {
        "id": "SCD",
        "name": "SCD"
      },
      "variant": {
        "id": "XL1000+",
        "name": "XL1000+",
        "fullName": "SCD XL1000+",
        "cycleTime": 29.41,
        "devicesPerBox": 12,
        "actualCycleTime": 59
      },
      "shiftId": "normal-time",
      "targets": {
        "hourly": 122,
        "daily": 989,
        "boxes": 82
      },
      "actual": {
        "total": 72,
        "boxes": 6,
        "progress": 7
      },
      "batches": [
        {
          "id": 26021959,
          "quantity": 72,
          "boxes": 6
        }
      ],
      "supervisors": [
        {
          "id": "Michaela",
          "name": "Michaela",
          "production": 72,
          "startTime": "07:30",
          "endTime": "08:41",
          "target": 144,
          "progress": 50
        }
      ],
      "timeline": [
        {
          "hour": "08:30",
          "target": 122,
          "actual": 72,
          "cumTarget": 122,
          "cumActual": 72,
          "transitionTarget": 0,
          "previousVariant": null,
          "previousVariantMinutes": 0,
          "currentVariantMinutes": 60
        },
        {
          "hour": "09:30",
          "target": 22,
          "actual": 0,
          "cumTarget": 144,
          "cumActual": 72,
          "transitionTarget": 22,
          "previousVariant": null,
          "previousVariantMinutes": 0,
          "currentVariantMinutes": 11
        }
      ]
    },
    {
      "id": "SCD-XL200SC",
      "product": {
        "id": "SCD",
        "name": "SCD"
      },
      "variant": {
        "id": "XL200SC",
        "name": "XL200SC",
        "fullName": "SCD XL200SC",
        "cycleTime": 65.45,
        "devicesPerBox": 15,
        "actualCycleTime": 1940
      },
      "shiftId": "normal-time",
      "targets": {
        "hourly": 55,
        "daily": 444,
        "boxes": 29
      },
      "actual": {
        "total": 15,
        "boxes": 1,
        "progress": 3
      },
      "batches": [
        {
          "id": 26021856,
          "quantity": 15,
          "boxes": 1
        }
      ],
      "supervisors": [
        {
          "id": "Siyabonga",
          "name": "Siyabonga",
          "production": 15,
          "startTime": "07:30",
          "endTime": "16:30",
          "target": 444,
          "progress": 3
        }
      ],
      "timeline": [
        {
          "hour": "08:30",
          "target": 55,
          "actual": 15,
          "cumTarget": 55,
          "cumActual": 15,
          "transitionTarget": 0,
          "previousVariant": null,
          "previousVariantMinutes": 0,
          "currentVariantMinutes": 60
        },
        {
          "hour": "09:30",
          "target": 55,
          "actual": 0,
          "cumTarget": 110,
          "cumActual": 15,
          "transitionTarget": 0,
          "previousVariant": null,
          "previousVariantMinutes": 0,
          "currentVariantMinutes": 60
        }
      ]
    },
    {
      "id": "Scalpel-PARC15S",
      "product": {
        "id": "Scalpel",
        "name": "Scalpel"
      },
      "variant": {
        "id": "PARC15S",
        "name": "PARC15S",
        "fullName": "Scalpel PARC15S",
        "cycleTime": 2.28,
        "devicesPerBox": 500,
        "actualCycleTime": 15
      },
      "shiftId": "normal-time",
      "targets": {
        "hourly": 1578,
        "daily": 12763,
        "boxes": 25
      },
      "actual": {
        "total": 2000,
        "boxes": 4,
        "progress": 16
      },
      "batches": [
        {
          "id": 26021854,
          "quantity": 2000,
          "boxes": 4
        }
      ],
      "supervisors": [
        {
          "id": "Apelele",
          "name": "Apelele",
          "production": 2000,
          "startTime": "07:30",
          "endTime": "16:30",
          "target": 12763,
          "progress": 16
        }
      ],
      "timeline": [
        {
          "hour": "08:30",
          "target": 1578,
          "actual": 500,
          "cumTarget": 1578,
          "cumActual": 500,
          "transitionTarget": 0,
          "previousVariant": null,
          "previousVariantMinutes": 0,
          "currentVariantMinutes": 60
        },
        {
          "hour": "09:30",
          "target": 1578,
          "actual": 1500,
          "cumTarget": 3156,
          "cumActual": 2000,
          "transitionTarget": 0,
          "previousVariant": null,
          "previousVariantMinutes": 0,
          "currentVariantMinutes": 60
        }
      ]
    }
  ],
  "summary": {
    "products": [
      {
        "id": "SCD",
        "name": "SCD",
        "totalProduction": 123,
        "totalTarget": 2422,
        "progress": 5
      },
      {
        "id": "Scalpel",
        "name": "Scalpel",
        "totalProduction": 2000,
        "totalTarget": 25526,
        "progress": 8
      }
    ],
    "supervisors": [
      {
        "id": "Michaela",
        "name": "Michaela",
        "totalProduction": 108,
        "totalTarget": 988,
        "progress": 11,
        "variants": [
          "SCD-XL1000+",
          "SCD-XL1000SC"
        ]
      },
      {
        "id": "Siyabonga",
        "name": "Siyabonga",
        "totalProduction": 15,
        "totalTarget": 444,
        "progress": 3,
        "variants": [
          "SCD-XL200SC"
        ]
      },
      {
        "id": "Apelele",
        "name": "Apelele",
        "totalProduction": 2000,
        "totalTarget": 12763,
        "progress": 16,
        "variants": [
          "Scalpel-PARC15S"
        ]
      }
    ]
  }
}